delayed_assert/__init__.py
delayed_assert/delayed_assert.py
delayed_assert-0.4.2.dist-info/licenses/LICENSE
delayed_assert-0.4.2.dist-info/METADATA
delayed_assert-0.4.2.dist-info/WHEEL
delayed_assert-0.4.2.dist-info/top_level.txt
delayed_assert-0.4.2.dist-info/RECORD
