Metadata-Version: 2.4
Name: delayed_assert
Version: 0.4.2
Summary: Delayed/soft assertions for python
Home-page: https://github.com/pr4bh4sh/python-delayed-assert
Author: pr4bh4sh
License-File: LICENSE
Dynamic: author
Dynamic: description
Dynamic: description-content-type
Dynamic: home-page
Dynamic: license-file
Dynamic: summary
